AUTHORS.rst
CONTRIBUTING.rst
HISTORY.rst
LICENSE
MANIFEST.in
README.rst
setup.cfg
setup.py
gitserver/__init__.py
gitserver/example.py
gitserver/server.py
gitserver/tap.py
gitserver/utils.py
gitserver.egg-info/PKG-INFO
gitserver.egg-info/SOURCES.txt
gitserver.egg-info/dependency_links.txt
gitserver.egg-info/entry_points.txt
gitserver.egg-info/not-zip-safe
gitserver.egg-info/requires.txt
gitserver.egg-info/top_level.txt
gitserver/security/__init__.py
gitserver/security/avatar.py
gitserver/security/checker.py
gitserver/security/realm.py
requirements/default.txt
requirements/docs.txt
requirements/testing.txt
tests/__init__.py
twisted/plugins/gitserver.py