Metadata-Version: 1.0
Name: gitserver
Version: 0.0.1
Summary: UNKNOWN
Home-page: https://github.com/aventurella/gitserver
Author: Adam Venturella <aventurella@gmail.com>
Author-email: aventurella@gmail.com
License: BSD
Platform: UNKNOWN
Classifier: Development Status :: 2 - Pre-Alpha
Classifier: Intended Audience :: Developers
Classifier: License :: OSI Approved :: BSD License
Classifier: Natural Language :: English
Classifier: Programming Language :: Python :: 2
Classifier: Programming Language :: Python :: 2.6
Classifier: Programming Language :: Python :: 2.7
Classifier: Programming Language :: Python :: 3
Classifier: Programming Language :: Python :: 3.3
